gcc_flags/__init__.py
gcc_flags/__main__.py
gcc_flags/gcc_flags.py
gcc_flags-0.1.1.dist-info/LICENSE
gcc_flags-0.1.1.dist-info/METADATA
gcc_flags-0.1.1.dist-info/WHEEL
gcc_flags-0.1.1.dist-info/entry_points.txt
gcc_flags-0.1.1.dist-info/top_level.txt
gcc_flags-0.1.1.dist-info/RECORD
