Metadata-Version: 2.1
Name: gcc-flags
Version: 0.1.1
Summary: Collect all possible C++ warning flags from GCC
Author-email: Niels Lohmann <mail@nlohmann.me>
License: MIT License        
Project-URL: Homepage, https://github.com/nlohmann/gcc_flags
Classifier: Development Status :: 5 - Production/Stable
Classifier: Environment :: Console
Classifier: Intended Audience :: Developers
Classifier: License :: OSI Approved :: MIT License
Classifier: Programming Language :: C++
Classifier: Topic :: Software Development :: Compilers
Requires-Python: >=3.7
License-File: LICENSE
Requires-Dist: termcolor (>=1.1.0)
